drivers/__init__.py
drivers/setting_driver.py
scrapers/__init__.py
scrapers/scraping_script.py
tests/__init__.py
tests/test_data_science_central.py
datascraping_article-0.1.dist-info/LICENSE.txt
datascraping_article-0.1.dist-info/METADATA
datascraping_article-0.1.dist-info/WHEEL
datascraping_article-0.1.dist-info/top_level.txt
datascraping_article-0.1.dist-info/RECORD
