Metadata-Version: 2.1
Name: datascraping-article
Version: 0.1
Summary: A python package for web scraping the latest articles on popular Data science blogs
Home-page: https://github.com/Chesta1/datascience_article_scrapping
Author: Chesta Dhingra
Author-email: chestadhingra25@gmail.com
License: MIT
License-File: LICENSE.txt
Requires-Dist: pandas
Requires-Dist: selenium
Requires-Dist: datetime
